eurostat/__init__.py
eurostat/__old_sdmx_interface__.py
eurostat/eurostat.py
eurostat-1.1.0.dist-info/LICENSE.txt
eurostat-1.1.0.dist-info/METADATA
eurostat-1.1.0.dist-info/WHEEL
eurostat-1.1.0.dist-info/top_level.txt
eurostat-1.1.0.dist-info/RECORD
